{"type":"FeatureCollection","features":[{"type":"Feature","geometry":{"type":"Point","coordinates":[-147.74144839819266,64.83721157760871]},"properties":{"property_city":"Fairbanks","property_state":"AK","street":"AIRPORT RD COWLEE","zip":99701,"mortgages":[{"proj_num":13042013,"name":"FAIRVIEW MANOR APTS","units":272,"amount":3080000,"first_payment_date":null,"holder_city":"Ny","holder_state":""}]}},{"type":"Feature","geometry":{"type":"Point","coordinates":[-147.7261505,64.84365701]},"properties":{"property_city":"Fairbanks","property_state":"AK","street":"SECOND LACEY","zip":99701,"mortgages":[{"proj_num":13042016,"name":"POLARIS APTS","units":144,"amount":1792708,"first_payment_date":null,"holder_city":"Ca","holder_state":"No Data Available"}]}},{"type":"Feature","geometry":{"type":"Point","coordinates":[-147.7162988,64.84126146]},"properties":{"property_city":"Fairbanks","property_state":"AK","street":"THIRD LACEY","zip":99701,"mortgages":[{"proj_num":13042011,"name":"NORTHWARD APTS","units":210,"amount":2494800,"first_payment_date":null,"holder_city":"Ny","holder_state":""}]}},{"type":"Feature","geometry":{"type":"Point","coordinates":[-147.7141305,64.83937932]},"properties":{"property_city":"Fairbanks","property_state":"AK","street":"10TH AND NOBLE","zip":99701,"mortgages":[{"proj_num":13042020,"name":"DIXON APTS","units":64,"amount":691200,"first_payment_date":null,"holder_city":"Ny","holder_state":"No Data Available"}]}}]}