{"type":"FeatureCollection","features":[{"type":"Feature","geometry":{"type":"Point","coordinates":[-147.7141305,64.839379319]},"properties":{"property_city":"FAIRBANKS","property_state":"AK","street":"10TH AND NOBLE","zip":99701,"mortgages":[{"proj_num":13042020,"name":"DIXON APTS","units":64,"amount":691200,"first_payment_date":{"year":1952,"month":4,"day":1},"holder_name":"NEW YORK LIFE INSURANCE CO","holder_city":"New York","holder_state":"NY"}]}},{"type":"Feature","geometry":{"type":"Point","coordinates":[-147.7261505,64.843657011]},"properties":{"property_city":"FAIRBANKS","property_state":"AK","street":"SECOND LACEY","zip":99701,"mortgages":[{"proj_num":13042016,"name":"POLARIS APTS","units":144,"amount":1792708,"first_payment_date":{"year":1952,"month":12,"day":1},"holder_name":"FANNIE MAE","holder_city":"Pasadena","holder_state":"CA"}]}},{"type":"Feature","geometry":{"type":"Point","coordinates":[-147.7162988,64.841261456]},"properties":{"property_city":"FAIRBANKS","property_state":"AK","street":"THIRD LACEY","zip":99701,"mortgages":[{"proj_num":13042011,"name":"NORTHWARD APTS","units":210,"amount":2494800,"first_payment_date":{"year":1951,"month":10,"day":1},"holder_name":"NEW YORK LIFE INSURANCE CO","holder_city":"New York","holder_state":"NY"}]}},{"type":"Feature","geometry":{"type":"Point","coordinates":[-147.7484704,64.836891053]},"properties":{"property_city":"FAIRBANKS","property_state":"AK","street":"AIRPORT RD COWLEE","zip":99701,"mortgages":[{"proj_num":13042013,"name":"FAIRVIEW MANOR APTS","units":272,"amount":3080000,"first_payment_date":{"year":1952,"month":8,"day":1},"holder_name":"INSTITUTIONAL SECURITIES CORP","holder_city":"New York","holder_state":"NY"}]}}]}