{"type":"FeatureCollection","features":[{"type":"Feature","geometry":{"type":"Point","coordinates":[-112.0360694,46.58857616]},"properties":{"property_city":"Helena","property_state":"MT","street":"320 NORTH WARREN","zip":59601,"mortgages":[{"proj_num":9340002,"name":"HUSTAD APARTMENTS","units":28,"amount":4,"first_payment_date":null,"holder_city":"Ga","holder_state":""}]}}]}