{"type":"FeatureCollection","features":[{"type":"Feature","geometry":{"type":"Point","coordinates":[-112.0360694,46.588576155]},"properties":{"property_city":"Helena","property_state":"MT","street":"320 NORTH WARREN","zip":59601,"mortgages":[{"proj_num":9340002,"name":"HUSTAD APARTMENTS","units":28,"amount":90000,"first_payment_date":{"year":1948,"month":8,"day":1},"holder_name":"AXA EQUITABLE LIFE INSURANCE C","holder_city":"Atlanta","holder_state":"GA"}]}}]}